[
  {
    "route": "/news",
    "screenshot": "/Users/miujiawei/Desktop/QuantGym/docs/browser-audit-screenshots/279-iab-news-external-inventory.png",
    "anchors": [],
    "bodyClass": "is-authenticated",
    "buttons": [
      "总览",
      "成长",
      "刷题",
      "社群",
      "求职",
      "资源",
      "设置",
      "0火焰日历",
      "0聊天",
      "Browser QA账号",
      "",
      "今日待办5"
    ],
    "headings": [],
    "horizontalOverflow": false,
    "overlay": false,
    "title": "QuantGym",
    "url": "http://127.0.0.1:5179/news"
  },
  {
    "route": "/jobs",
    "screenshot": "/Users/miujiawei/Desktop/QuantGym/docs/browser-audit-screenshots/280-iab-jobs-external-inventory.png",
    "anchors": [],
    "bodyClass": "is-authenticated",
    "buttons": [
      "总览",
      "成长",
      "刷题",
      "社群",
      "求职",
      "资源",
      "设置",
      "0火焰日历",
      "0聊天",
      "Browser QA账号",
      "",
      "今日待办5"
    ],
    "headings": [],
    "horizontalOverflow": false,
    "overlay": false,
    "title": "QuantGym",
    "url": "http://127.0.0.1:5179/jobs"
  },
  {
    "route": "/companies",
    "screenshot": "/Users/miujiawei/Desktop/QuantGym/docs/browser-audit-screenshots/281-iab-companies-external-inventory.png",
    "anchors": [],
    "bodyClass": "is-authenticated",
    "buttons": [
      "总览",
      "成长",
      "刷题",
      "社群",
      "求职",
      "资源",
      "设置",
      "0火焰日历",
      "0聊天",
      "Browser QA账号",
      "",
      "今日待办5"
    ],
    "headings": [],
    "horizontalOverflow": false,
    "overlay": false,
    "title": "QuantGym",
    "url": "http://127.0.0.1:5179/companies"
  },
  {
    "route": "/courses",
    "screenshot": "/Users/miujiawei/Desktop/QuantGym/docs/browser-audit-screenshots/282-iab-courses-external-inventory.png",
    "anchors": [],
    "bodyClass": "is-authenticated",
    "buttons": [
      "总览",
      "成长",
      "刷题",
      "社群",
      "求职",
      "资源",
      "设置",
      "0火焰日历",
      "0聊天",
      "Browser QA账号",
      "",
      "今日待办5"
    ],
    "headings": [],
    "horizontalOverflow": false,
    "overlay": false,
    "title": "QuantGym",
    "url": "http://127.0.0.1:5179/courses"
  },
  {
    "route": "/resume",
    "screenshot": "/Users/miujiawei/Desktop/QuantGym/docs/browser-audit-screenshots/283-iab-resume-inventory.png",
    "anchors": [],
    "bodyClass": "is-authenticated",
    "buttons": [
      "总览",
      "成长",
      "刷题",
      "社群",
      "求职",
      "资源",
      "设置",
      "0火焰日历",
      "0聊天",
      "Browser QA账号",
      "",
      "今日待办5"
    ],
    "headings": [],
    "horizontalOverflow": false,
    "overlay": false,
    "title": "QuantGym",
    "url": "http://127.0.0.1:5179/resume"
  },
  {
    "route": "/settings",
    "screenshot": "/Users/miujiawei/Desktop/QuantGym/docs/browser-audit-screenshots/284-iab-settings-google-inventory.png",
    "anchors": [],
    "bodyClass": "is-authenticated",
    "buttons": [
      "总览",
      "成长",
      "刷题",
      "社群",
      "求职",
      "资源",
      "设置",
      "0火焰日历",
      "0聊天",
      "Browser QA账号",
      "",
      "今日待办5"
    ],
    "headings": [],
    "horizontalOverflow": false,
    "overlay": false,
    "title": "QuantGym",
    "url": "http://127.0.0.1:5179/settings"
  }
]